{
  "name": "juicy-popover",
  "description": "Custom Element that expands an area when clicked on a handle",
  "homepage": "https://github.com/Juicy/juicy-popover",
  "license": "MIT",
  "main": "src/juicy-popover.html",
  "keywords": [
    "web-components",
    "dropdown",
    "popover",
    "tooltip",
    "combo box",
    "combo",
    "combobox"
  ],
  "ignore": [
    "**/.*",
    "bower_components"
  ],
  "dependencies": {
    "webcomponentsjs": "^0.7.22"
  },
  "_release": "f5e54d83a3",
  "_resolution": {
    "type": "branch",
    "branch": "gh-pages",
    "commit": "f5e54d83a3f8e9c7d86e1dc3c7f9e7465e30b732"
  },
  "_source": "git://github.com/Juicy/juicy-popover.git",
  "_target": "gh-pages",
  "_originalSource": "Juicy/juicy-popover"
}